restructure/__init__.py
restructure/combine.py
restructure/locate.py
restructure/merge.py
restructure/restructure.py
restructure-0.2.0.dist-info/LICENSE
restructure-0.2.0.dist-info/METADATA
restructure-0.2.0.dist-info/WHEEL
restructure-0.2.0.dist-info/top_level.txt
restructure-0.2.0.dist-info/RECORD
