Metadata-Version: 2.1
Name: restructure
Version: 0.2.0
Summary: Restructure dictionary values by key
Author-email: dstodev <dstodev@gmail.com>
Project-URL: Source, https://github.com/dstodev/restructure
Classifier: Programming Language :: Python :: 3
Classifier: License :: OSI Approved :: MIT License
Classifier: Operating System :: OS Independent
Requires-Python: >=3.6
License-File: LICENSE
